<font>
  <info face="font" size="150" bold="1" italic="0" charset="" unicode="" stretchH="100" smooth="1" aa="1" padding="2,2,2,2" spacing="0,0" outline="0"/>
  <common lineHeight="209" base="140" scaleW="1320" scaleH="512" pages="1" packed="0"/>
  <pages>
    <page id="0" file="font.png"/>
  </pages>
  <chars count="75">
    <char id="97" x="2" y="2" width="74" height="90" xoffset="7" yoffset="52" xadvance="91" page="0" chnl="15"/>
    <char id="618" x="2" y="94" width="62" height="79" xoffset="8" yoffset="57" xadvance="78" page="0" chnl="15"/>
    <char id="44" x="2" y="175" width="36" height="63" xoffset="10" yoffset="109" xadvance="53" page="0" chnl="15"/>
    <char id="650" x="2" y="240" width="83" height="81" xoffset="6" yoffset="57" xadvance="94" page="0" chnl="15"/>
    <char id="593" x="66" y="94" width="82" height="90" xoffset="6" yoffset="52" xadvance="99" page="0" chnl="15"/>
    <char id="58" x="78" y="2" width="32" height="88" xoffset="11" yoffset="53" xadvance="53" page="0" chnl="15"/>
    <char id="101" x="112" y="2" width="77" height="90" xoffset="6" yoffset="52" xadvance="89" page="0" chnl="15"/>
    <char id="601" x="2" y="323" width="76" height="82" xoffset="5" yoffset="56" xadvance="85" page="0" chnl="15"/>
    <char id="105" x="80" y="323" width="31" height="125" xoffset="9" yoffset="15" xadvance="48" page="0" chnl="15"/>
    <char id="117" x="87" y="186" width="78" height="88" xoffset="10" yoffset="54" xadvance="98" page="0" chnl="15"/>
    <char id="230" x="150" y="94" width="121" height="90" xoffset="8" yoffset="52" xadvance="135" page="0" chnl="15"/>
    <char id="596" x="191" y="2" width="66" height="82" xoffset="9" yoffset="56" xadvance="78" page="0" chnl="15"/>
    <char id="594" x="259" y="2" width="79" height="82" xoffset="10" yoffset="56" xadvance="93" page="0" chnl="15"/>
    <char id="604" x="2" y="407" width="68" height="82" xoffset="5" yoffset="56" xadvance="77" page="0" chnl="15"/>
    <char id="652" x="113" y="276" width="77" height="79" xoffset="6" yoffset="57" xadvance="88" page="0" chnl="15"/>
    <char id="98" x="113" y="357" width="82" height="122" xoffset="11" yoffset="19" xadvance="99" page="0" chnl="15"/>
    <char id="100" x="192" y="186" width="82" height="122" xoffset="6" yoffset="19" xadvance="99" page="0" chnl="15"/>
    <char id="114" x="273" y="86" width="58" height="88" xoffset="11" yoffset="52" xadvance="70" page="0" chnl="15"/>
    <char id="122" x="197" y="310" width="69" height="86" xoffset="7" yoffset="54" xadvance="80" page="0" chnl="15"/>
    <char id="658" x="268" y="310" width="69" height="113" xoffset="10" yoffset="57" xadvance="87" page="0" chnl="15"/>
    <char id="102" x="276" y="176" width="60" height="122" xoffset="4" yoffset="17" xadvance="60" page="0" chnl="15"/>
    <char id="103" x="338" y="86" width="84" height="124" xoffset="6" yoffset="52" xadvance="92" page="0" chnl="15"/>
    <char id="104" x="339" y="212" width="78" height="120" xoffset="11" yoffset="19" xadvance="99" page="0" chnl="15"/>
    <char id="106" x="339" y="334" width="47" height="158" xoffset="-7" yoffset="15" xadvance="48" page="0" chnl="15"/>
    <char id="107" x="388" y="334" width="80" height="120" xoffset="11" yoffset="19" xadvance="95" page="0" chnl="15"/>
    <char id="108" x="424" y="2" width="37" height="122" xoffset="11" yoffset="19" xadvance="50" page="0" chnl="15"/>
    <char id="109" x="419" y="212" width="127" height="88" xoffset="11" yoffset="52" xadvance="150" page="0" chnl="15"/>
    <char id="110" x="470" y="302" width="78" height="88" xoffset="11" yoffset="52" xadvance="99" page="0" chnl="15"/>
    <char id="112" x="463" y="2" width="82" height="119" xoffset="11" yoffset="52" xadvance="99" page="0" chnl="15"/>
    <char id="115" x="197" y="398" width="65" height="90" xoffset="7" yoffset="52" xadvance="76" page="0" chnl="15"/>
    <char id="116" x="470" y="392" width="60" height="110" xoffset="3" yoffset="31" xadvance="67" page="0" chnl="15"/>
    <char id="643" x="547" y="2" width="77" height="146" xoffset="-11" yoffset="24" xadvance="53" page="0" chnl="15"/>
    <char id="118" x="463" y="123" width="82" height="86" xoffset="5" yoffset="54" xadvance="91" page="0" chnl="15"/>
    <char id="119" x="532" y="392" width="123" height="86" xoffset="6" yoffset="54" xadvance="134" page="0" chnl="15"/>
    <char id="240" x="548" y="150" width="81" height="127" xoffset="7" yoffset="15" xadvance="96" page="0" chnl="15"/>
    <char id="331" x="626" y="2" width="74" height="115" xoffset="10" yoffset="56" xadvance="92" page="0" chnl="15"/>
    <char id="952" x="631" y="119" width="79" height="124" xoffset="8" yoffset="17" xadvance="95" page="0" chnl="15"/>
    <char id="113" x="631" y="245" width="82" height="119" xoffset="6" yoffset="52" xadvance="99" page="0" chnl="15"/>
    <char id="121" x="657" y="366" width="82" height="119" xoffset="5" yoffset="54" xadvance="91" page="0" chnl="15"/>
    <char id="111" x="702" y="2" width="84" height="90" xoffset="6" yoffset="52" xadvance="96" page="0" chnl="15"/>
    <char id="120" x="550" y="279" width="78" height="86" xoffset="6" yoffset="54" xadvance="90" page="0" chnl="15"/>
    <char id="99" x="712" y="94" width="68" height="90" xoffset="6" yoffset="52" xadvance="80" page="0" chnl="15"/>
    <char id="49" x="715" y="186" width="71" height="112" xoffset="12" yoffset="28" xadvance="91" page="0" chnl="15"/>
    <char id="50" x="741" y="300" width="78" height="114" xoffset="6" yoffset="25" xadvance="91" page="0" chnl="15"/>
    <char id="51" x="788" y="2" width="77" height="116" xoffset="7" yoffset="25" xadvance="91" page="0" chnl="15"/>
    <char id="52" x="788" y="120" width="84" height="112" xoffset="3" yoffset="28" xadvance="91" page="0" chnl="15"/>
    <char id="53" x="867" y="2" width="77" height="114" xoffset="7" yoffset="28" xadvance="91" page="0" chnl="15"/>
    <char id="54" x="821" y="234" width="79" height="116" xoffset="7" yoffset="25" xadvance="91" page="0" chnl="15"/>
    <char id="55" x="874" y="118" width="77" height="112" xoffset="8" yoffset="28" xadvance="91" page="0" chnl="15"/>
    <char id="56" x="821" y="352" width="78" height="116" xoffset="7" yoffset="25" xadvance="91" page="0" chnl="15"/>
    <char id="57" x="901" y="352" width="79" height="116" xoffset="6" yoffset="25" xadvance="91" page="0" chnl="15"/>
    <char id="48" x="902" y="232" width="79" height="116" xoffset="6" yoffset="25" xadvance="91" page="0" chnl="15"/>
    <char id="96" x="72" y="450" width="38" height="38" xoffset="18" yoffset="0" xadvance="96" page="0" chnl="15"/>
    <char id="33" x="982" y="350" width="32" height="117" xoffset="14" yoffset="24" xadvance="59" page="0" chnl="15"/>
    <char id="64" x="953" y="2" width="140" height="146" xoffset="8" yoffset="24" xadvance="156" page="0" chnl="15"/>
    <char id="35" x="983" y="150" width="81" height="112" xoffset="6" yoffset="28" xadvance="91" page="0" chnl="15"/>
    <char id="36" x="1016" y="264" width="72" height="147" xoffset="9" yoffset="11" xadvance="91" page="0" chnl="15"/>
    <char id="37" x="1090" y="150" width="140" height="116" xoffset="4" yoffset="25" xadvance="150" page="0" chnl="15"/>
    <char id="94" x="264" y="425" width="69" height="69" xoffset="11" yoffset="24" xadvance="91" page="0" chnl="15"/>
    <char id="38" x="1095" y="2" width="107" height="116" xoffset="4" yoffset="25" xadvance="116" page="0" chnl="15"/>
    <char id="42" x="741" y="416" width="64" height="62" xoffset="8" yoffset="17" xadvance="79" page="0" chnl="15"/>
    <char id="40" x="1090" y="268" width="37" height="152" xoffset="12" yoffset="16" xadvance="60" page="0" chnl="15"/>
    <char id="41" x="1129" y="268" width="37" height="152" xoffset="12" yoffset="16" xadvance="60" page="0" chnl="15"/>
    <char id="45" x="2" y="491" width="43" height="19" xoffset="7" yoffset="86" xadvance="57" page="0" chnl="15"/>
    <char id="61" x="340" y="2" width="80" height="60" xoffset="6" yoffset="53" xadvance="91" page="0" chnl="15"/>
    <char id="43" x="1016" y="422" width="80" height="82" xoffset="6" yoffset="42" xadvance="91" page="0" chnl="15"/>
    <char id="46" x="982" y="469" width="32" height="33" xoffset="11" yoffset="108" xadvance="53" page="0" chnl="15"/>
    <char id="47" x="1168" y="268" width="47" height="150" xoffset="4" yoffset="18" xadvance="58" page="0" chnl="15"/>
    <char id="59" x="1204" y="2" width="36" height="118" xoffset="10" yoffset="54" xadvance="53" page="0" chnl="15"/>
    <char id="34" x="1098" y="422" width="69" height="59" xoffset="13" yoffset="22" xadvance="95" page="0" chnl="15"/>
    <char id="39" x="953" y="150" width="27" height="59" xoffset="13" yoffset="22" xadvance="53" page="0" chnl="15"/>
    <char id="123" x="1217" y="268" width="47" height="148" xoffset="5" yoffset="18" xadvance="60" page="0" chnl="15"/>
    <char id="91" x="1242" y="2" width="37" height="148" xoffset="15" yoffset="18" xadvance="60" page="0" chnl="15"/>
    <char id="125" x="1266" y="152" width="47" height="148" xoffset="8" yoffset="18" xadvance="60" page="0" chnl="15"/>
    <char id="93" x="1281" y="2" width="37" height="148" xoffset="8" yoffset="18" xadvance="60" page="0" chnl="15"/>
    <char id="32" x="0" y="0" width="0" height="0" xoffset="8" yoffset="18" xadvance="34" page="0" chnl="15"/>
  </chars>
</font>